tbint_logger/__init__.py
tbint_logger/tbint_logger.py
tbint_logger-0.5.0.dist-info/licenses/LICENSE
tbint_logger-0.5.0.dist-info/METADATA
tbint_logger-0.5.0.dist-info/WHEEL
tbint_logger-0.5.0.dist-info/top_level.txt
tbint_logger-0.5.0.dist-info/RECORD
