Metadata-Version: 2.4
Name: tbint-logger
Version: 0.5.0
Summary: A simple logger for tbint projects
Author-email: Marco Kellershoff <marco.kellershoff@tbint.de>
License-Expression: MIT
Project-URL: Homepage, https://bitbucket.org/tbint/tbint-logger-py
Project-URL: Issues, https://bitbucket.org/tbint/tbint-logger-py/issues
Classifier: Programming Language :: Python :: 3
Classifier: Operating System :: OS Independent
Requires-Python: >=3.8
License-File: LICENSE
Requires-Dist: aiohttp
Requires-Dist: python-dotenv
Requires-Dist: requests
Requires-Dist: google-cloud-logging
Dynamic: license-file
